setup.py
three_3_distributions/Binomialdistribution.py
three_3_distributions/Gaussiandistribution.py
three_3_distributions/Generaldistribution.py
three_3_distributions/__init__.py
three_3_distributions.egg-info/PKG-INFO
three_3_distributions.egg-info/SOURCES.txt
three_3_distributions.egg-info/dependency_links.txt
three_3_distributions.egg-info/not-zip-safe
three_3_distributions.egg-info/top_level.txt