Metadata-Version: 1.0
Name: three-3-distributions
Version: 0.1
Summary: Gaussian distributions
Home-page: UNKNOWN
Author: Dayanand Ghelaro
Author-email: dayanandghelaro@gmail.com
License: UNKNOWN
Platform: UNKNOWN
